[
  {
    "name": "UwUTools",
	"fileExtension": "exe",
	"exeName": "UwUTools.exe",
	"run": "false",
    "url": "https://github.com/dpadGuy/UwUTools_Binaries/releases/download/UwUToolsBinaries/UwUTools.exe"
  },
  {
    "name": "Mozilla Firefox",
	"fileExtension": "zip",
	"exeName": "firefox.exe",
	"run": "false",
    "url": "https://github.com/dpadGuy/SalsaNOWThings/releases/download/Things/Mozilla.Firefox.zip"
  },
  {
    "name": "System Informer",
	"fileExtension": "zip",
	"exeName": "systeminformer.exe",
	"run": "false",
    "url": "https://github.com/dpadGuy/SalsaNOWThings/releases/download/Things/System.Informer.zip"
  },
    {
    "name": "Explorer++",
	"fileExtension": "exe",
	"exeName": "Explorer++.exe",
	"run": "false",
    "url": "https://github.com/dpadGuy/SalsaNOWThings/releases/download/Things/Explorer++.exe"
  },
  {
    "name": "7-Zip",
	"fileExtension": "zip",
	"exeName": "7zFM.exe",
	"run": "false",
    "url": "https://github.com/dpadGuy/SalsaNOWThings/releases/download/Things/7-Zip.zip"
  },
  {
    "name": "Notepad++",
	"fileExtension": "zip",
	"exeName": "notepad++.exe",
	"run": "false",
    "url": "https://github.com/dpadGuy/SalsaNOWThings/releases/download/Things/Notepad++.zip"
  },
  {
	"name": "FDM",
	"fileExtension": "zip",
	"exeName": "fdm.exe",
	"run": "false",
    "url": "https://github.com/dpadGuy/SalsaNOWThings/releases/download/Things/FDM.zip"
  },
  {
	"name": "qBittorrent",
	"fileExtension": "zip",
	"exeName": "qbittorrent.exe",
	"run": "false",
    "url": "https://github.com/dpadGuy/SalsaNOWThings/releases/download/Things/qBittorrent.zip"
  },
]



